tbusd/__init__.py
tbusd/client.py
tbusd/exceptions.py
tbusd-0.1.1.dist-info/licenses/LICENSE
tbusd-0.1.1.dist-info/METADATA
tbusd-0.1.1.dist-info/WHEEL
tbusd-0.1.1.dist-info/top_level.txt
tbusd-0.1.1.dist-info/RECORD
