Metadata-Version: 2.4
Name: tbusd
Version: 0.1.1
Summary: Python SDK for TBUSD gasless transfers
Author-email: TBUSD <support@tbusd.io>
License: MIT
Project-URL: Homepage, https://tbusd.io
Project-URL: Documentation, https://tbusd.io/developers
Project-URL: Repository, https://github.com/tbusd/tbusd-python
Keywords: tbusd,stablecoin,ethereum,base,gasless,web3
Classifier: Development Status :: 4 - Beta
Classifier: Intended Audience :: Developers
Classifier: License :: OSI Approved :: MIT License
Classifier: Programming Language :: Python :: 3
Classifier: Programming Language :: Python :: 3.8
Classifier: Programming Language :: Python :: 3.9
Classifier: Programming Language :: Python :: 3.10
Classifier: Programming Language :: Python :: 3.11
Classifier: Programming Language :: Python :: 3.12
Classifier: Topic :: Software Development :: Libraries :: Python Modules
Requires-Python: >=3.8
License-File: LICENSE
Requires-Dist: requests>=2.25.0
Requires-Dist: eth-account>=0.8.0
Requires-Dist: eth-abi>=4.0.0
Provides-Extra: dev
Requires-Dist: pytest>=7.0.0; extra == "dev"
Requires-Dist: pytest-asyncio>=0.20.0; extra == "dev"
Dynamic: license-file
